Metadata-Version: 2.1
Name: numpy-typing
Version: 1.1.1
Summary: Improved numpy typing anotations
Author: Pirolley Melvyn
Author-email: 
Keywords: python,numpy,typing,type hinting
Classifier: Programming Language :: Python :: 3
Classifier: Operating System :: MacOS :: MacOS X
Classifier: Operating System :: Microsoft :: Windows
Classifier: Operating System :: POSIX :: Linux
Classifier: License :: OSI Approved :: MIT License
